saet_sockjs_tornado-2.0.1-py3.11-nspkg.pth
sockjs/tornado/__init__.py
sockjs/tornado/basehandler.py
sockjs/tornado/conn.py
sockjs/tornado/migrate.py
sockjs/tornado/periodic.py
sockjs/tornado/proto.py
sockjs/tornado/router.py
sockjs/tornado/session.py
sockjs/tornado/sessioncontainer.py
sockjs/tornado/static.py
sockjs/tornado/stats.py
sockjs/tornado/util.py
sockjs/tornado/websocket.py
sockjs/tornado/transports/__init__.py
sockjs/tornado/transports/base.py
sockjs/tornado/transports/eventsource.py
sockjs/tornado/transports/htmlfile.py
sockjs/tornado/transports/jsonp.py
sockjs/tornado/transports/pollingbase.py
sockjs/tornado/transports/rawwebsocket.py
sockjs/tornado/transports/streamingbase.py
sockjs/tornado/transports/websocket.py
sockjs/tornado/transports/xhr.py
sockjs/tornado/transports/xhrstreaming.py
saet_sockjs_tornado-2.0.1.dist-info/LICENSE
saet_sockjs_tornado-2.0.1.dist-info/METADATA
saet_sockjs_tornado-2.0.1.dist-info/WHEEL
saet_sockjs_tornado-2.0.1.dist-info/namespace_packages.txt
saet_sockjs_tornado-2.0.1.dist-info/top_level.txt
saet_sockjs_tornado-2.0.1.dist-info/RECORD
