Metadata-Version: 2.1
Name: saet-sockjs-tornado
Version: 2.0.1
Summary: SockJS python server implementation on top of Tornado framework
Home-page: https://github.com/saet/sockjs-tornado
Author: Serge S. Koval
Author-email: serge.koval@gmail.com
License: MIT License
Classifier: License :: OSI Approved :: MIT License
Classifier: Programming Language :: Python :: 3.11
Classifier: Programming Language :: Python :: Implementation :: CPython
Requires: tornado
License-File: LICENSE
Requires-Dist: tornado >=6.0.0
